datamaker/__about__.py
datamaker/__init__.py
datamaker/custom_providers.py
datamaker/fake.py
datamaker/generation.py
datamaker/schema.py
datamaker/sorting.py
datamaker/utils/casing.py
datamaker_core-0.0.0.dist-info/METADATA
datamaker_core-0.0.0.dist-info/WHEEL
datamaker_core-0.0.0.dist-info/licenses/LICENSE
datamaker_core-0.0.0.dist-info/licenses/LICENSE.txt
datamaker_core-0.0.0.dist-info/RECORD
